{"name":"1-100france","tagline":"","body":"<!doctype html>\r\n\r\n<html lang=\"nl\">\r\n\r\n<html>\r\n<head>frans 1-100</head><body>\r\n<h1>frans leren</h1>\r\n\r\n0:<input type=\"text\" id=\"0\" value=\"\" size=12>\r\n<br><input type=\"button\" value=\"laat antwoord zien\" onclick=\"document.getElementById('0').value='zero';\">\r\n<br>\r\n1:<input type=\"text\" id=\"1\" value=\"\" size=12>\r\n<br><input type=\"button\" value=\"laat antwoord zien\" onclick=\"document.getElementById('1').value='un, une';\">\r\n<br>\r\n2:<input type=\"text\" id=\"2\" value=\"\" size=12>\r\n<br><input type=\"button\" value=\"laat antwoord zien\" onclick=\"document.getElementById('2').value='deux';\">\r\n    <br>\r\n3:<input type=\"text\" id=\"3\" value=\"\" size=12>\r\n<br><input type=\"button\" value=\"laat antwoord zien\" onclick=\"document.getElementById('3').value='trois';\">\r\n    <br>\r\n4:<input type=\"text\" id=\"4\" value=\"\" size=12>\r\n<br><input type=\"button\" value=\"laat antwoord zien\" onclick=\"document.getElementById('4').value='quatre';\">\r\n    <br>\r\n5:<input type=\"text\" id=\"5\" value=\"\" size=12>\r\n<br><input type=\"button\" value=\"laat antwoord zien\" onclick=\"document.getElementById('5').value='cinq';\">\r\n    <br>\r\n6:<input type=\"text\" id=\"6\" value=\"\" size=12>\r\n<br><input type=\"button\" value=\"laat antwoord zien\" onclick=\"document.getElementById('6').value='six';\">\r\n    <br>\r\n7:<input type=\"text\" id=\"7\" value=\"\" size=12>\r\n<br><input type=\"button\" value=\"laat antwoord zien\" onclick=\"document.getElementById('7').value='sept';\">\r\n    <br>\r\n8:<input type=\"text\" id=\"8\" value=\"\" size=12>\r\n<br><input type=\"button\" value=\"laat antwoord zien\" onclick=\"document.getElementById('8').value='huit';\">\r\n    <br>\r\n9:<input type=\"text\" id=\"9\" value=\"\" size=12>\r\n<br><input type=\"button\" value=\"laat antwoord zien\" onclick=\"document.getElementById('9').value='neuf';\">\r\n    <br>\r\n10:<input type=\"text\" id=\"10\" value=\"\" size=12>\r\n<br><input type=\"button\" value=\"laat antwoord zien\" onclick=\"document.getElementById('10').value='dix';\">\r\n    <br>\r\n11:<input type=\"text\" id=\"11\" value=\"\" size=12>\r\n<br><input type=\"button\" value=\"laat antwoord zien\" onclick=\"document.getElementById('11').value='onze';\">\r\n    <br>\r\n12:<input type=\"text\" id=\"12\" value=\"\" size=12>\r\n<br><input type=\"button\" value=\"laat antwoord zien\" onclick=\"document.getElementById('12').value='douze';\">\r\n    <br>\r\n13:<input type=\"text\" id=\"13\" value=\"\" size=12>\r\n<br><input type=\"button\" value=\"laat antwoord zien\" onclick=\"document.getElementById('13').value='treize';\">\r\n    <br>\r\n14:<input type=\"text\" id=\"14\" value=\"\" size=12>\r\n<br><input type=\"button\" value=\"laat antwoord zien\" onclick=\"document.getElementById('14').value='quatorze';\">\r\n    <br>\r\n15:<input type=\"text\" id=\"15\" value=\"\" size=12>\r\n<br><input type=\"button\" value=\"laat antwoord zien\" onclick=\"document.getElementById('15').value='quinze';\">\r\n    <br>\r\n16:<input type=\"text\" id=\"16\" value=\"\" size=12>\r\n<br><input type=\"button\" value=\"laat antwoord zien\" onclick=\"document.getElementById('16').value='seize';\">\r\n    <br>\r\n17:<input type=\"text\" id=\"17\" value=\"\" size=12>\r\n<br><input type=\"button\" value=\"laat antwoord zien\" onclick=\"document.getElementById('17').value='dix-sept';\">\r\n    <br>\r\n18:<input type=\"text\" id=\"18\" value=\"\" size=12>\r\n<br><input type=\"button\" value=\"laat antwoord zien\" onclick=\"document.getElementById('18').value='dix-huit';\">\r\n    <br>\r\n19:<input type=\"text\" id=\"19\" value=\"\" size=12>\r\n<br><input type=\"button\" value=\"laat antwoord zien\" onclick=\"document.getElementById('19').value='dix-neuf';\">\r\n    <br>\r\n20:<input type=\"text\" id=\"20\" value=\"\" size=12>\r\n<br><input type=\"button\" value=\"laat antwoord zien\" onclick=\"document.getElementById('20').value='vingt';\">\r\n\r\n</body></html>","google":"","note":"Don't delete this file! It's used internally to help with page regeneration."}